dynamic_cast-0.1.2a2.dist-info/METADATA
dynamic_cast-0.1.2a2.dist-info/WHEEL
dynamic_cast-0.1.2a2.dist-info/entry_points.txt
dynamic_cast-0.1.2a2.dist-info/licenses/LICENSE
dynamic_cast/__init__.py
dynamic_cast/__main__.py
dynamic_cast/async_cast.py
dynamic_cast/dynamic_cast.py
dynamic_cast/utils/__init__.py
dynamic_cast/utils/_builtins.py
dynamic_cast/utils/_typing.py
dynamic_cast-0.1.2a2.dist-info/RECORD
