Metadata-Version: 2.1
Name: dynamic-cast
Version: 0.1.2a2
Summary: A Python library for flexible type casting of function arguments and return values based on type annotations.
Keywords: type-casting,type-annotations,dynamic-typing,python-type-hints,type-conversion,function-arguments,type-checking,callable-type,data-types,type-safety,python-decorators,runtime-type-checking,type-inference,generic-types,automatic-type-casting,type-system
Author-Email: Santiago Papiernik <spapiernik12@gmail.com>
License: MIT License
Classifier: License :: OSI Approved :: MIT License
Classifier: Intended Audience :: Developers
Classifier: Programming Language :: Python :: 3.8
Classifier: Programming Language :: Python :: 3.9
Classifier: Programming Language :: Python :: 3.10
Classifier: Programming Language :: Python :: 3.11
Classifier: Programming Language :: Python :: 3.12
Classifier: Typing :: Typed
Project-URL: Repository, https://github.com/Cxx-mlr/dynamic-cast
Requires-Python: >=3.8
Requires-Dist: packaging>=24.1
Requires-Dist: typing-extensions>=4.12.2
